LICENSE
MANIFEST.in
README.md
setup.cfg
setup.py
api/__init__.py
api/authentication.py
api/authorisation.py
api/decorators.py
api/exceptions.py
api/filtering.py
api/helpers.py
api/settings.py
api/urls.py
api/utils.py
api/mixins/__init__.py
api/mixins/authentication.py
api/mixins/authorisation.py
api/mixins/models.py
api/mixins/packing.py
api/mixins/resources.py
api/mixins/serialisation.py
api/resources/__init__.py
api/resources/base.py
api/resources/decorators.py
api/resources/links.py
api/resources/manager.py
api/resources/models.py
api/views/__init__.py
api/views/models.py
podiant_api.egg-info/PKG-INFO
podiant_api.egg-info/SOURCES.txt
podiant_api.egg-info/dependency_links.txt
podiant_api.egg-info/not-zip-safe
podiant_api.egg-info/top_level.txt